dohq_teamcity/__init__.py
dohq_teamcity/api_client.py
dohq_teamcity/configuration.py
dohq_teamcity/rest.py
dohq_teamcity/version.py
dohq_teamcity/api/__init__.py
dohq_teamcity/api/agent_api.py
dohq_teamcity/api/agent_pool_api.py
dohq_teamcity/api/build_api.py
dohq_teamcity/api/build_queue_api.py
dohq_teamcity/api/build_type_api.py
dohq_teamcity/api/change_api.py
dohq_teamcity/api/debug_api.py
dohq_teamcity/api/default_api.py
dohq_teamcity/api/federation_api.py
dohq_teamcity/api/group_api.py
dohq_teamcity/api/investigation_api.py
dohq_teamcity/api/mute_api.py
dohq_teamcity/api/problem_api.py
dohq_teamcity/api/problem_occurrence_api.py
dohq_teamcity/api/project_api.py
dohq_teamcity/api/server_api.py
dohq_teamcity/api/test_api.py
dohq_teamcity/api/test_occurrence_api.py
dohq_teamcity/api/user_api.py
dohq_teamcity/api/vcs_root_api.py
dohq_teamcity/api/vcs_root_instance_api.py
dohq_teamcity/custom/__init__.py
dohq_teamcity/custom/api.py
dohq_teamcity/custom/base_model.py
dohq_teamcity/custom/client.py
dohq_teamcity/custom/models.py
dohq_teamcity/models/__init__.py
dohq_teamcity/models/agent.py
dohq_teamcity/models/agent_pool.py
dohq_teamcity/models/agent_pools.py
dohq_teamcity/models/agent_requirement.py
dohq_teamcity/models/agent_requirements.py
dohq_teamcity/models/agents.py
dohq_teamcity/models/artifact_dependencies.py
dohq_teamcity/models/artifact_dependency.py
dohq_teamcity/models/authorized_info.py
dohq_teamcity/models/backup_process.py
dohq_teamcity/models/backup_process_info.py
dohq_teamcity/models/backup_process_manager.py
dohq_teamcity/models/branch.py
dohq_teamcity/models/branch_version.py
dohq_teamcity/models/branches.py
dohq_teamcity/models/build.py
dohq_teamcity/models/build_cancel_request.py
dohq_teamcity/models/build_change.py
dohq_teamcity/models/build_changes.py
dohq_teamcity/models/build_triggering_options.py
dohq_teamcity/models/build_type.py
dohq_teamcity/models/build_types.py
dohq_teamcity/models/builds.py
dohq_teamcity/models/change.py
dohq_teamcity_fopina_fork-1.0.8.dist-info/LICENSE
dohq_teamcity_fopina_fork-1.0.8.dist-info/METADATA
dohq_teamcity_fopina_fork-1.0.8.dist-info/WHEEL
dohq_teamcity_fopina_fork-1.0.8.dist-info/top_level.txt
dohq_teamcity_fopina_fork-1.0.8.dist-info/RECORD
